Metadata-Version: 2.1
Name: singan-seg-polyp
Version: 1.0.7
Summary: Generating synthetic polyps and corresponding mask using pretrained SinGAN-Seg and Style tranfering functionalities.
Home-page: https://github.com/vlbthambawita/singan-seg-polyp
Author: Vajira Thambawita
Author-email: vlbthambawita@gmail.com
License: UNKNOWN
Platform: UNKNOWN
Classifier: Programming Language :: Python :: 3
Classifier: License :: OSI Approved :: MIT License
Classifier: Operating System :: OS Independent
Requires-Python: >=3.6
License-File: LICENSE
Requires-Dist: numpy
Requires-Dist: tqdm
Requires-Dist: pandas
Requires-Dist: pathlib
Requires-Dist: PyYAML
Requires-Dist: scipy
Requires-Dist: scikit-image
Requires-Dist: scikit-learn
Requires-Dist: requests
Requires-Dist: natsort
